comparison/__init__.py
comparison/xbbo_benchmark.py
xbbo/__init__.py
xbbo/run_benchmark.py
xbbo/acquisition_function/__init__.py
xbbo/acquisition_function/acq_func.py
xbbo/acquisition_function/acq_optimizer.py
xbbo/acquisition_function/base.py
xbbo/acquisition_function/transfer/__init__.py
xbbo/acquisition_function/transfer/mogp.py
xbbo/acquisition_function/transfer/taf.py
xbbo/alg_auxiliary/__init__.py
xbbo/alg_auxiliary/lamcts/Classifier.py
xbbo/alg_auxiliary/lamcts/MCTS.py
xbbo/alg_auxiliary/lamcts/Node.py
xbbo/alg_auxiliary/lamcts/__init__.py
xbbo/alg_auxiliary/lamcts/utils.py
xbbo/alg_auxiliary/lamcts/latent_space/__init__.py
xbbo/alg_auxiliary/lamcts/latent_space/model_identity.py
xbbo/alg_auxiliary/lamcts/latent_space/model_pca.py
xbbo/configspace/__init__.py
xbbo/configspace/abstract_feature_space.py
xbbo/configspace/space.py
xbbo/core/__init__.py
xbbo/core/constants.py
xbbo/core/register.py
xbbo/core/stochastic.py
xbbo/core/trials.py
xbbo/datasets/__init__.py
xbbo/initial_design/__init__.py
xbbo/initial_design/base.py
xbbo/initial_design/default_configuration_design.py
xbbo/initial_design/factorial_design.py
xbbo/initial_design/latin_hypercube_design.py
xbbo/initial_design/random_design.py
xbbo/initial_design/sobol_design.py
xbbo/pipeline/__init__.py
xbbo/pipeline/bbo_benchmark.py
xbbo/problem/__init__.py
xbbo/problem/base.py
xbbo/problem/fast_example_problem.py
xbbo/problem/transfer_problem.py
xbbo/search_algorithm/__init__.py
xbbo/search_algorithm/anneal_optimizer.py
xbbo/search_algorithm/base.py
xbbo/search_algorithm/bo_optimizer.py
xbbo/search_algorithm/bore_optimizer.py
xbbo/search_algorithm/cem_optimizer.py
xbbo/search_algorithm/cma_optimizer.py
xbbo/search_algorithm/de_optimizer.py
xbbo/search_algorithm/lamcts.py
xbbo/search_algorithm/lfbo_optimizer.py
xbbo/search_algorithm/pbt_optimizer.py
xbbo/search_algorithm/pso_optimizer.py
xbbo/search_algorithm/random_optimizer.py
xbbo/search_algorithm/regularizedEA_optimizer.py
XBBO-0.3.3.dist-info/LICENSE
XBBO-0.3.3.dist-info/METADATA
XBBO-0.3.3.dist-info/WHEEL
XBBO-0.3.3.dist-info/top_level.txt
XBBO-0.3.3.dist-info/RECORD
