Metadata-Version: 2.1
Name: XBBO
Version: 0.3.3
Summary: A Python toolbox for performing Black-Box Optimization.
Home-page: https://git.openi.org.cn/PCL_AutoML/XBBO
Author: (LeiZhang)XMU-MAC Lab
Author-email: leizhang@stu.xmu.edu.cn
License: MIT
Classifier: License :: OSI Approved :: MIT License
Classifier: Programming Language :: Python
Classifier: Programming Language :: Python :: 3
Classifier: Programming Language :: Python :: 3.7
Classifier: Programming Language :: Python :: Implementation :: CPython
Classifier: Programming Language :: Python :: Implementation :: PyPy
Requires-Python: >=3.7.0
License-File: LICENSE
Requires-Dist: scipy >=1.7.0
Requires-Dist: scikit-optimize >=0.8.1
Requires-Dist: pyyaml >=6.0
Requires-Dist: numpy >=1.20.3
Requires-Dist: pandas >=1.2.5
Requires-Dist: ConfigSpace ==0.4.19
Requires-Dist: scikit-learn >=0.22.1
Requires-Dist: yacs >=0.1.8
Requires-Dist: statsmodels >=0.13.1
Requires-Dist: cma >=3.2.2
Provides-Extra: dev
Requires-Dist: pyrfr >=0.5.0 ; extra == 'dev'
Requires-Dist: pytest >=6.2.4 ; extra == 'dev'
Requires-Dist: prettytable >=3.2.0 ; extra == 'dev'
Requires-Dist: seaborn ; extra == 'dev'
Requires-Dist: glob ; extra == 'dev'
Requires-Dist: xgboost ; extra == 'dev'
